CHANGES.txt
MANIFEST.in
README.rst
setup.py
dbdump/__init__.py
dbdump/management/__init__.py
dbdump/management/commands/__init__.py
dbdump/management/commands/dbdump.py
django_dbdump.egg-info/PKG-INFO
django_dbdump.egg-info/SOURCES.txt
django_dbdump.egg-info/dependency_links.txt
django_dbdump.egg-info/requires.txt
django_dbdump.egg-info/top_level.txt