Metadata-Version: 1.0
Name: django-dbdump
Version: 1.1
Summary: Database backup management command.
Home-page: https://github.com/vitaliyf/django-dbdump/
Author: Vitaliy Fuks
Author-email: vitaliyf@gmail.com
License: BSD
Download-URL: https://github.com/vitaliyf/django-dbdump/
Platform: any
Classifier: Framework :: Django
Classifier: Intended Audience :: Developers
Classifier: Intended Audience :: System Administrators
Classifier: License :: OSI Approved :: BSD License
Classifier: Operating System :: OS Independent
Classifier: Programming Language :: Python
